morf/__init__.py
morf/utils/__init__.py
morf/utils/alerts.py
morf/utils/api_utils.py
morf/utils/caching.py
morf/utils/config.py
morf/utils/docker.py
morf/utils/doi.py
morf/utils/job_runner_utils.py
morf/utils/log.py
morf/utils/s3interface.py
morf/utils/security.py
morf/utils/submit.py
morf/workflow/__init__.py
morf/workflow/cross_validation.py
morf/workflow/evaluate.py
morf/workflow/extract.py
morf/workflow/test.py
morf/workflow/train.py
morf_api-0.5.1.dist-info/DESCRIPTION.rst
morf_api-0.5.1.dist-info/METADATA
morf_api-0.5.1.dist-info/RECORD
morf_api-0.5.1.dist-info/WHEEL
morf_api-0.5.1.dist-info/metadata.json
morf_api-0.5.1.dist-info/top_level.txt
